transformers_collection/__init__.py
transformers_collection/__main__.py
transformers_collection/config_loader.py
transformers_collection/models/base.py
transformers_collection/models/models.py
transformers_collection-0.2.0.dist-info/METADATA
transformers_collection-0.2.0.dist-info/entry_points.txt
transformers_collection-0.2.0.dist-info/WHEEL
transformers_collection-0.2.0.dist-info/LICENSE
transformers_collection-0.2.0.dist-info/RECORD
