Metadata-Version: 2.1
Name: transformers-collection
Version: 0.2.0
Summary: A collection of transformer models built  using huggingface for various tasks.
Home-page: https://github.com/aadhithya/transformers-collection
License: MIT
Keywords: transformers,huggingface,NLP
Author: Aadhithya Sankar
Author-email: aadhithya.s@outlook.com
Requires-Python: >=3.9,<3.11
Classifier: License :: OSI Approved :: MIT License
Classifier: Programming Language :: Python :: 3
Classifier: Programming Language :: Python :: 3.9
Classifier: Programming Language :: Python :: 3.10
Classifier: Topic :: Scientific/Engineering :: Artificial Intelligence
Requires-Dist: datasets (>=2.8.0,<3.0.0)
Requires-Dist: evaluate (>=0.4.0,<0.5.0)
Requires-Dist: loguru (>=0.6.0,<0.7.0)
Requires-Dist: munch (>=2.5.0,<3.0.0)
Requires-Dist: numpy (>=1.24.1,<2.0.0)
Requires-Dist: pytorch-lightning (>=1.9.0,<2.0.0)
Requires-Dist: scikit-learn (>=1.2.1,<2.0.0)
Requires-Dist: scipy (>=1.10.0,<2.0.0)
Requires-Dist: tensorboard (>=2.11.2,<3.0.0)
Requires-Dist: torch (>1.10,<2.0)
Requires-Dist: transformers (>=4.26.0,<5.0.0)
Requires-Dist: typer (>=0.7.0,<0.8.0)
Project-URL: Repository, https://github.com/aadhithya/transformers-collection
